ttool/__init__.py
ttool/jira_utils/__init__.py
ttool/jira_utils/jira_issue_to_github_branch.py
ttool/jira_utils/main.py
ttool/jira_utils/set_up.py
ttool/jira_utils/utils.py
ttool/main.py
ttool-0.2.2.dist-info/LICENSE
ttool-0.2.2.dist-info/WHEEL
ttool-0.2.2.dist-info/entry_points.txt
ttool-0.2.2.dist-info/METADATA
ttool-0.2.2.dist-info/RECORD
