Metadata-Version: 2.1
Name: ttool
Version: 0.2.2
Summary: Tugys utils tools
License: MIT
Author: IamTugy
Author-email: tugmica@gmail.com
Requires-Python: >=3.8
Classifier: License :: OSI Approved :: MIT License
Classifier: Programming Language :: Python :: 3
Classifier: Programming Language :: Python :: 3.8
Classifier: Programming Language :: Python :: 3.9
Classifier: Programming Language :: Python :: 3.10
Classifier: Programming Language :: Python :: 3.11
Requires-Dist: PyYAML (>=6.0,<7.0)
Requires-Dist: dacite (>=1.7.0,<2.0.0)
Requires-Dist: docopt (>=0.6.2,<0.7.0)
Requires-Dist: inquirer (>=3.1.2,<4.0.0)
Requires-Dist: jira (>=3.4.1,<4.0.0)
Requires-Dist: requests-toolbelt (>=0.10.1,<0.11.0)
Requires-Dist: typer (>=0.7.0,<0.8.0)
